{
  "article_schema_version": "1.0",
  "id": 12,
  "info": {
    "author": "WebMaster",
    "date": "2023-05-20",
    "category": "announcement"
  },
  "title": "Katsura Sunshine's Rakugo",
  "content": "<p>JAFAX is proud to bring Katsura Sunshine to Grand Rapids for the first time!</p><p>In 2008, he became the 15th apprentice to the great Rakugo Master Katsura Bunshi VI, from whom he received the name Katsura Sunshine.</p><p>Sunshine was the first ever Western Rakugo-ka in the Kamigata tradition (Osaka / Kyoto) and only the second in Japanese history, after his predecessor Kairakute Burakku a hundred years before.</p><p>Read through his bio <a href=\"/guests/KatsuraSunshine\">here!</a></p>"
}
